Metadata-Version: 2.1
Name: x-magical
Version: 0.0.4
Summary: X-MAGICAL is a benchmark suite for cross-embodiment visual imitation.
Home-page: https://github.com/kevinzakka/x-magical/
Author: Kevin Zakka
License: ISC
Requires-Python: >=3.8
License-File: LICENSE
Requires-Dist: absl-py
Requires-Dist: gym
Requires-Dist: numpy
Requires-Dist: pygame
Requires-Dist: pyglet
Requires-Dist: pymunk (~=5.6.0)
Requires-Dist: Pillow
Provides-Extra: dev
Requires-Dist: ipdb ; extra == 'dev'
Requires-Dist: jupyter ; extra == 'dev'
Requires-Dist: black ; extra == 'dev'
Requires-Dist: isort ; extra == 'dev'
Requires-Dist: flake8 ; extra == 'dev'
Requires-Dist: pytest-xdist ; extra == 'dev'
Requires-Dist: pytype ; extra == 'dev'
Provides-Extra: test
Requires-Dist: pytest-xdist ; extra == 'test'
Requires-Dist: pytype ; extra == 'test'
